README.rst
setup.cfg
setup.py
hoss.egg-info/PKG-INFO
hoss.egg-info/SOURCES.txt
hoss.egg-info/dependency_links.txt
hoss.egg-info/entry_points.txt
hoss.egg-info/not-zip-safe
hoss.egg-info/requires.txt
hoss.egg-info/top_level.txt
hoss_agent/__init__.py
hoss_agent/base.py
hoss_agent/processors.py
hoss_agent/version.py
hoss_agent/conf/__init__.py
hoss_agent/conf/constants.py
hoss_agent/context/__init__.py
hoss_agent/context/base.py
hoss_agent/context/contextvars.py
hoss_agent/context/threadlocal.py
hoss_agent/contrib/__init__.py
hoss_agent/contrib/async_worker.py
hoss_agent/instrumentation/__init__.py
hoss_agent/instrumentation/control.py
hoss_agent/instrumentation/packages/__init__.py
hoss_agent/instrumentation/packages/httpclient_hooks.py
hoss_agent/instrumentation/packages/urllib3_hooks.py
hoss_agent/middleware/__init__.py
hoss_agent/middleware/tornado/__init__.py
hoss_agent/transport/__init__.py
hoss_agent/transport/base.py
hoss_agent/transport/exceptions.py
hoss_agent/transport/http.py
hoss_agent/transport/http_base.py
hoss_agent/utils/__init__.py
hoss_agent/utils/buffer_proxy.py
hoss_agent/utils/bytes_key_to_string.py
hoss_agent/utils/compat.py
hoss_agent/utils/encoding.py
hoss_agent/utils/json_encoder.py
hoss_agent/utils/logging.py
hoss_agent/utils/module_import.py
hoss_agent/utils/read_proxy.py
hoss_agent/utils/runtime_env.py
hoss_agent/utils/threading.py
tests/instrumentations/__init__.py
tests/instrumentations/test_requests.py
tests/instrumentations/test_urllib3.py