Metadata-Version: 2.1
Name: hoss
Version: 1.1.2
Summary: UNKNOWN
Home-page: https://github.com/hoss/python-agent
Author: Hoss
License: BSD
Platform: UNKNOWN
Classifier: Intended Audience :: Developers
Classifier: Intended Audience :: System Administrators
Classifier: Operating System :: OS Independent
Classifier: Topic :: Software Development
Classifier: Programming Language :: Python
Classifier: Programming Language :: Python :: 2.7
Classifier: Programming Language :: Python :: 3.5
Classifier: Programming Language :: Python :: 3.6
Classifier: Programming Language :: Python :: 3.7
Classifier: Programming Language :: Python :: 3.8
Classifier: Programming Language :: Python :: Implementation :: CPython
Classifier: Programming Language :: Python :: Implementation :: PyPy
Classifier: License :: OSI Approved :: BSD License
Provides-Extra: flask
Provides-Extra: tests
Provides-Extra: opentracing
Provides-Extra: starlette
Provides-Extra: aiohttp
Provides-Extra: tornado
